sfu/__init__.py
sfu/sfu.py
sfu-2.0.0.dist-info/LICENSE
sfu-2.0.0.dist-info/METADATA
sfu-2.0.0.dist-info/WHEEL
sfu-2.0.0.dist-info/top_level.txt
sfu-2.0.0.dist-info/RECORD
