Metadata-Version: 2.1
Name: sfu
Version: 2.0.0
Summary: Snowflake URI utility library that supports extraction of Snowflake configuration data and method parameters from Snowflake resource URIs.
Home-page: https://github.com/nthparty/sfu
Author: Ben Getchell
Author-email: ben@nthparty.com
License: MIT
Project-URL: Bug Tracker, https://github.com/nthparty/sfu/issues
Platform: any
Classifier: Programming Language :: Python :: 3
Classifier: Programming Language :: Python :: 3.7
Classifier: Programming Language :: Python :: 3.8
Classifier: Programming Language :: Python :: 3.9
Classifier: Programming Language :: Python :: 3.10
Classifier: License :: OSI Approved :: MIT License
Classifier: Operating System :: OS Independent
Requires-Python: >=3.7
License-File: LICENSE
